<?xml version="1.0" encoding="UTF-8"?>
<metadata xml:lang="en"><Esri><CreaDate>20130131</CreaDate><CreaTime>12593300</CreaTime><ArcGISFormat>1.0</ArcGISFormat><ArcGISstyle>FGDC CSDGM Metadata</ArcGISstyle><SyncOnce>FALSE</SyncOnce><RematchLocator>Address_Locator<Category Locator="Review">Address</Category><Description Locator="Review">Locator style for US addresses</Description><MinimumMatchScore Locator="Review">85</MinimumMatchScore><MinimumCandidateScore Locator="Review">10</MinimumCandidateScore><SpellingSensitivity Locator="Review">80</SpellingSensitivity><IntersectionConnectors Locator="Review">&amp; @ |</IntersectionConnectors><MatchIfScoresTie Locator="Review">-1</MatchIfScoresTie><WriteXYCoordFields Locator="Review">-1</WriteXYCoordFields><WriteStandardizedAddressField Locator="Review">0</WriteStandardizedAddressField><WriteReferenceIDField Locator="Review">-1</WriteReferenceIDField><WriteAdditionalOutputFields Locator="Review">-1</WriteAdditionalOutputFields><WritePercentAlongField Locator="Review">0</WritePercentAlongField><RuntimeMemoryLimit Locator="Review">512000000</RuntimeMemoryLimit><ShowElapsedTime Locator="Review">0</ShowElapsedTime><StorageSegmentSizeKB Locator="Review">128</StorageSegmentSizeKB><supportsEmptyHouseNumber Locator="Review">0</supportsEmptyHouseNumber><supportsIntersections Locator="Review">false</supportsIntersections><StoreStandardizedRefData Locator="Review">true</StoreStandardizedRefData><BatchPresortInputs Locator="Review">State</BatchPresortInputs><BatchPresortInputs Locator="Review">ZIP</BatchPresortInputs><BatchPresortInputs Locator="Review">City</BatchPresortInputs><CLSID Locator="Review">{DA70B7E3-10B2-42E3-BFF7-6C81355862BC}</CLSID><LocatorWorkspaceString Locator="Review">ProgID = esriDataSourcesFile.ShapefileWorkspaceFactory.1; Path = C:\Geocoder\</LocatorWorkspaceString><RebuildStartTime Locator="Review">129769652287250000</RebuildStartTime><RebuildStartTimeAscii Locator="Review">8:33:48 AM</RebuildStartTimeAscii><SafeLocatorName Locator="Review">Address_Locator</SafeLocatorName><UICLSID Locator="Review">{AE5A3A0E-F756-11D2-9F4F-00C04F8ED1C4}</UICLSID><SideOffset Locator="Review">0</SideOffset><SideOffsetUnits Locator="Review">ReferenceDataUnits</SideOffsetUnits><EndOffset Locator="Review">0</EndOffset><EndOffsetUnits Locator="Review">ReferenceDataUnits</EndOffsetUnits><UseRelativePaths Locator="Review">-1</UseRelativePaths><InTable Locator="Review">::</InTable><InKeyColumns Locator="Review">::</InKeyColumns><InColumns Locator="Review">ARC_Street</InColumns><InColumns Locator="Review">ARC_City</InColumns><InColumns Locator="Review">ARC_State</InColumns><InColumns Locator="Review">ARC_ZIP</InColumns><OutTable Locator="Review">::</OutTable><OutKeyColumns Locator="Review">::</OutKeyColumns><OutColumns Locator="Review">Shape</OutColumns><OutColumns Locator="Review">Status</OutColumns><OutColumns Locator="Review">Score</OutColumns><OutColumns Locator="Review">Match_addr</OutColumns><OutColumns Locator="Review">Ref_ID</OutColumns><OutColumns Locator="Review">X</OutColumns><OutColumns Locator="Review">Y</OutColumns><OutColumns Locator="Review">User_fld</OutColumns><OutColumns Locator="Review">Addr_type</OutColumns></RematchLocator><DataProperties><lineage><Process ToolSource="c:\program files (x86)\arcgis\desktop10.0\ArcToolbox\Toolboxes\Network Analyst Tools.tbx\CalculateLocations" Date="20121105" Time="092458">CalculateLocations CommHealth_Geocoding Roads_2012_CLEAN_ND "5000 Meters" "Roads_2012_CLEAN SHAPE;Roads_2012_CLEAN_ND_Junctions NONE" MATCH_TO_CLOSEST SourceID SourceOID PosAlong SideOfEdge SnapX SnapY Distance # # INCLUDE "Roads_2012_CLEAN #;Roads_2012_CLEAN_ND_Junctions #"</Process><Process ToolSource="C:\Program Files\ArcGIS\Desktop10.0\ArcToolbox\Toolboxes\Analysis Tools.tbx\Clip" Date="20121120" Time="140341">Clip CommHealth_Geocoding "Medicare Local - North West Inner Melbourne" C:\AURIN_Project\HealthProject\Data\Health.mdb\CommHealthCentres_ML #</Process></lineage><itemProps><itemName Sync="TRUE">CommHealthCentres_ML</itemName><imsContentType Sync="TRUE">002</imsContentType><itemLocation><linkage Sync="TRUE">file://\\400D-86127\C$\AURIN_Project\HealthProject\Data\Health.mdb</linkage><protocol Sync="TRUE">Local Area Network</protocol></itemLocation></itemProps><coordRef><type Sync="TRUE">Geographic</type><geogcsn Sync="TRUE">GCS_GDA_1994</geogcsn><peXml Sync="TRUE">&lt;GeographicCoordinateSystem xsi:type='typens:GeographicCoordinateSystem' xmlns:xsi='http://www.w3.org/2001/XMLSchema-instance' xmlns:xs='http://www.w3.org/2001/XMLSchema' xmlns:typens='http://www.esri.com/schemas/ArcGIS/10.0'&gt;&lt;WKT&gt;GEOGCS[&amp;quot;GCS_GDA_1994&amp;quot;,DATUM[&amp;quot;D_GDA_1994&amp;quot;,SPHEROID[&amp;quot;GRS_1980&amp;quot;,6378137.0,298.257222101]],PRIMEM[&amp;quot;Greenwich&amp;quot;,0.0],UNIT[&amp;quot;Degree&amp;quot;,0.0174532925199433],AUTHORITY[&amp;quot;EPSG&amp;quot;,4283]]&lt;/WKT&gt;&lt;XOrigin&gt;-399.99999999999989&lt;/XOrigin&gt;&lt;YOrigin&gt;-399.99999999999989&lt;/YOrigin&gt;&lt;XYScale&gt;1111948722.2222221&lt;/XYScale&gt;&lt;ZOrigin&gt;-100000&lt;/ZOrigin&gt;&lt;ZScale&gt;10000&lt;/ZScale&gt;&lt;MOrigin&gt;-100000&lt;/MOrigin&gt;&lt;MScale&gt;10000&lt;/MScale&gt;&lt;XYTolerance&gt;8.9831528411952117e-009&lt;/XYTolerance&gt;&lt;ZTolerance&gt;0.001&lt;/ZTolerance&gt;&lt;MTolerance&gt;0.001&lt;/MTolerance&gt;&lt;HighPrecision&gt;true&lt;/HighPrecision&gt;&lt;LeftLongitude&gt;-180&lt;/LeftLongitude&gt;&lt;WKID&gt;4283&lt;/WKID&gt;&lt;/GeographicCoordinateSystem&gt;</peXml></coordRef></DataProperties><SyncDate>20121120</SyncDate><SyncTime>14034100</SyncTime><ModDate>20121120</ModDate><ModTime>14034100</ModTime></Esri><dataIdInfo><envirDesc Sync="TRUE">Microsoft Windows XP Version 5.1 (Build 2600) Service Pack 3; ESRI ArcGIS 10.0.0.2414</envirDesc><dataLang><languageCode value="en" country="AU"></languageCode></dataLang><idCitation><resTitle Sync="TRUE">CommHealthCentres_ML</resTitle><presForm><PresFormCd value="005"></PresFormCd></presForm></idCitation><descKeys><thesaName uuidref="723f6998-058e-11dc-8314-0800200c9a66"></thesaName><keyword Sync="TRUE">002</keyword></descKeys><spatRpType><SpatRepTypCd value="001"></SpatRepTypCd></spatRpType></dataIdInfo><mdLang><languageCode value="en"></languageCode></mdLang><distInfo><distFormat><formatName Sync="TRUE">Personal GeoDatabase Feature Class</formatName></distFormat></distInfo><mdHrLv><ScopeCd value="005"></ScopeCd></mdHrLv><mdHrLvName Sync="TRUE">dataset</mdHrLvName><refSysInfo><RefSystem><refSysID><identCode code="4283"></identCode><idCodeSpace Sync="TRUE">EPSG</idCodeSpace><idVersion Sync="TRUE">7.4.1</idVersion></refSysID></RefSystem></refSysInfo><spdoinfo><ptvctinf><esriterm Name="CommHealthCentres_ML"><efeatyp Sync="TRUE">Simple</efeatyp><efeageom Sync="TRUE">1</efeageom><esritopo Sync="TRUE">FALSE</esritopo><efeacnt Sync="TRUE">0</efeacnt><spindex Sync="TRUE">TRUE</spindex><linrefer Sync="TRUE">FALSE</linrefer></esriterm></ptvctinf></spdoinfo><spatRepInfo><VectSpatRep><topLvl><TopoLevCd value="001"></TopoLevCd></topLvl><geometObjs><geoObjTyp><GeoObjTypCd value="004"></GeoObjTypCd><geoObjCnt Sync="TRUE">0</geoObjCnt></geoObjTyp></geometObjs></VectSpatRep></spatRepInfo><eainfo><detailed Name="CommHealthCentres_ML"><enttyp><enttypl Sync="TRUE">CommHealthCentres_ML</enttypl><enttypt Sync="TRUE">Feature Class</enttypt><enttypc Sync="TRUE">0</enttypc></enttyp><attr><attrlabl Sync="TRUE">OBJECTID</attrlabl><attalias Sync="TRUE">OBJECTID</attalias><attrtype Sync="TRUE">OID</attrtype><attwidth Sync="TRUE">4</attwidth><atprecis Sync="TRUE">0</atprecis><attscale Sync="TRUE">0</attscale><attrdef Sync="TRUE">Internal feature number.</attrdef><attrdefs Sync="TRUE">ESRI</attrdefs><attrdomv><udom Sync="TRUE">Sequential unique whole numbers that are automatically generated.</udom></attrdomv></attr><attr><attrlabl Sync="TRUE">Shape</attrlabl><attalias Sync="TRUE">Shape</attalias><attrtype Sync="TRUE">Geometry</attrtype><attwidth Sync="TRUE">0</attwidth><atprecis Sync="TRUE">0</atprecis><attscale Sync="TRUE">0</attscale><attrdef Sync="TRUE">Feature geometry.</attrdef><attrdefs Sync="TRUE">ESRI</attrdefs><attrdomv><udom Sync="TRUE">Coordinates defining the features.</udom></attrdomv></attr><attr><attrlabl Sync="TRUE">Status</attrlabl><attalias Sync="TRUE">Status</attalias><attrtype Sync="TRUE">String</attrtype><attwidth Sync="TRUE">1</attwidth><atprecis Sync="TRUE">0</atprecis><attscale Sync="TRUE">0</attscale></attr><attr><attrlabl Sync="TRUE">Score</attrlabl><attalias Sync="TRUE">Score</attalias><attrtype Sync="TRUE">Double</attrtype><attwidth Sync="TRUE">8</attwidth><atprecis Sync="TRUE">0</atprecis><attscale Sync="TRUE">0</attscale></attr><attr><attrlabl Sync="TRUE">Match_type</attrlabl><attalias Sync="TRUE">Match_type</attalias><attrtype Sync="TRUE">String</attrtype><attwidth Sync="TRUE">2</attwidth><atprecis Sync="TRUE">0</atprecis><attscale Sync="TRUE">0</attscale></attr><attr><attrlabl Sync="TRUE">Match_addr</attrlabl><attalias Sync="TRUE">Match_addr</attalias><attrtype Sync="TRUE">String</attrtype><attwidth Sync="TRUE">120</attwidth><atprecis Sync="TRUE">0</atprecis><attscale Sync="TRUE">0</attscale></attr><attr><attrlabl Sync="TRUE">Ref_ID</attrlabl><attalias Sync="TRUE">Ref_ID</attalias><attrtype Sync="TRUE">Integer</attrtype><attwidth Sync="TRUE">4</attwidth><atprecis Sync="TRUE">0</atprecis><attscale Sync="TRUE">0</attscale></attr><attr><attrlabl Sync="TRUE">X</attrlabl><attalias Sync="TRUE">X</attalias><attrtype Sync="TRUE">Double</attrtype><attwidth Sync="TRUE">8</attwidth><atprecis Sync="TRUE">0</atprecis><attscale Sync="TRUE">0</attscale></attr><attr><attrlabl Sync="TRUE">Y</attrlabl><attalias Sync="TRUE">Y</attalias><attrtype Sync="TRUE">Double</attrtype><attwidth Sync="TRUE">8</attwidth><atprecis Sync="TRUE">0</atprecis><attscale Sync="TRUE">0</attscale></attr><attr><attrlabl Sync="TRUE">User_fld</attrlabl><attalias Sync="TRUE">User_fld</attalias><attrtype Sync="TRUE">String</attrtype><attwidth Sync="TRUE">120</attwidth><atprecis Sync="TRUE">0</atprecis><attscale Sync="TRUE">0</attscale></attr><attr><attrlabl Sync="TRUE">Addr_type</attrlabl><attalias Sync="TRUE">Addr_type</attalias><attrtype Sync="TRUE">String</attrtype><attwidth Sync="TRUE">20</attwidth><atprecis Sync="TRUE">0</atprecis><attscale Sync="TRUE">0</attscale></attr><attr><attrlabl Sync="TRUE">ARC_Street</attrlabl><attalias Sync="TRUE">ARC_Street</attalias><attrtype Sync="TRUE">String</attrtype><attwidth Sync="TRUE">100</attwidth><atprecis Sync="TRUE">0</atprecis><attscale Sync="TRUE">0</attscale></attr><attr><attrlabl Sync="TRUE">ARC_City</attrlabl><attalias Sync="TRUE">ARC_City</attalias><attrtype Sync="TRUE">String</attrtype><attwidth Sync="TRUE">40</attwidth><atprecis Sync="TRUE">0</atprecis><attscale Sync="TRUE">0</attscale></attr><attr><attrlabl Sync="TRUE">ARC_State</attrlabl><attalias Sync="TRUE">ARC_State</attalias><attrtype Sync="TRUE">String</attrtype><attwidth Sync="TRUE">20</attwidth><atprecis Sync="TRUE">0</atprecis><attscale Sync="TRUE">0</attscale></attr><attr><attrlabl Sync="TRUE">ARC_ZIP</attrlabl><attalias Sync="TRUE">ARC_ZIP</attalias><attrtype Sync="TRUE">String</attrtype><attwidth Sync="TRUE">10</attwidth><atprecis Sync="TRUE">0</atprecis><attscale Sync="TRUE">0</attscale></attr><attr><attrlabl Sync="TRUE">ID</attrlabl><attalias Sync="TRUE">ID</attalias><attrtype Sync="TRUE">String</attrtype><attwidth Sync="TRUE">254</attwidth><atprecis Sync="TRUE">0</atprecis><attscale Sync="TRUE">0</attscale></attr><attr><attrlabl Sync="TRUE">F_Region</attrlabl><attalias Sync="TRUE">F_Region</attalias><attrtype Sync="TRUE">String</attrtype><attwidth Sync="TRUE">254</attwidth><atprecis Sync="TRUE">0</atprecis><attscale Sync="TRUE">0</attscale></attr><attr><attrlabl Sync="TRUE">F_Org</attrlabl><attalias Sync="TRUE">F_Org</attalias><attrtype Sync="TRUE">String</attrtype><attwidth Sync="TRUE">254</attwidth><atprecis Sync="TRUE">0</atprecis><attscale Sync="TRUE">0</attscale></attr><attr><attrlabl Sync="TRUE">F_Service</attrlabl><attalias Sync="TRUE">F_Service</attalias><attrtype Sync="TRUE">String</attrtype><attwidth Sync="TRUE">254</attwidth><atprecis Sync="TRUE">0</atprecis><attscale Sync="TRUE">0</attscale></attr><attr><attrlabl Sync="TRUE">F_OrgType</attrlabl><attalias Sync="TRUE">F_OrgType</attalias><attrtype Sync="TRUE">String</attrtype><attwidth Sync="TRUE">254</attwidth><atprecis Sync="TRUE">0</atprecis><attscale Sync="TRUE">0</attscale></attr><attr><attrlabl Sync="TRUE">F_URL</attrlabl><attalias Sync="TRUE">F_URL</attalias><attrtype Sync="TRUE">String</attrtype><attwidth Sync="TRUE">254</attwidth><atprecis Sync="TRUE">0</atprecis><attscale Sync="TRUE">0</attscale></attr><attr><attrlabl Sync="TRUE">F_Address</attrlabl><attalias Sync="TRUE">F_Address</attalias><attrtype Sync="TRUE">String</attrtype><attwidth Sync="TRUE">254</attwidth><atprecis Sync="TRUE">0</atprecis><attscale Sync="TRUE">0</attscale></attr><attr><attrlabl Sync="TRUE">F_Suburb</attrlabl><attalias Sync="TRUE">F_Suburb</attalias><attrtype Sync="TRUE">String</attrtype><attwidth Sync="TRUE">254</attwidth><atprecis Sync="TRUE">0</atprecis><attscale Sync="TRUE">0</attscale></attr><attr><attrlabl Sync="TRUE">F_State</attrlabl><attalias Sync="TRUE">F_State</attalias><attrtype Sync="TRUE">String</attrtype><attwidth Sync="TRUE">254</attwidth><atprecis Sync="TRUE">0</atprecis><attscale Sync="TRUE">0</attscale></attr><attr><attrlabl Sync="TRUE">F_Postcode</attrlabl><attalias Sync="TRUE">F_Postcode</attalias><attrtype Sync="TRUE">Double</attrtype><attwidth Sync="TRUE">8</attwidth><atprecis Sync="TRUE">0</atprecis><attscale Sync="TRUE">0</attscale></attr><attr><attrlabl Sync="TRUE">F_Position</attrlabl><attalias Sync="TRUE">F_Position</attalias><attrtype Sync="TRUE">String</attrtype><attwidth Sync="TRUE">254</attwidth><atprecis Sync="TRUE">0</atprecis><attscale Sync="TRUE">0</attscale></attr><attr><attrlabl Sync="TRUE">F_CEOTitle</attrlabl><attalias Sync="TRUE">F_CEOTitle</attalias><attrtype Sync="TRUE">String</attrtype><attwidth Sync="TRUE">254</attwidth><atprecis Sync="TRUE">0</atprecis><attscale Sync="TRUE">0</attscale></attr><attr><attrlabl Sync="TRUE">F_CEOName</attrlabl><attalias Sync="TRUE">F_CEOName</attalias><attrtype Sync="TRUE">String</attrtype><attwidth Sync="TRUE">254</attwidth><atprecis Sync="TRUE">0</atprecis><attscale Sync="TRUE">0</attscale></attr><attr><attrlabl Sync="TRUE">F_CEOSurna</attrlabl><attalias Sync="TRUE">F_CEOSurna</attalias><attrtype Sync="TRUE">String</attrtype><attwidth Sync="TRUE">254</attwidth><atprecis Sync="TRUE">0</atprecis><attscale Sync="TRUE">0</attscale></attr><attr><attrlabl Sync="TRUE">F_Email</attrlabl><attalias Sync="TRUE">F_Email</attalias><attrtype Sync="TRUE">String</attrtype><attwidth Sync="TRUE">254</attwidth><atprecis Sync="TRUE">0</atprecis><attscale Sync="TRUE">0</attscale></attr><attr><attrlabl Sync="TRUE">F_Phone</attrlabl><attalias Sync="TRUE">F_Phone</attalias><attrtype Sync="TRUE">String</attrtype><attwidth Sync="TRUE">254</attwidth><atprecis Sync="TRUE">0</atprecis><attscale Sync="TRUE">0</attscale></attr><attr><attrlabl Sync="TRUE">F_Lat</attrlabl><attalias Sync="TRUE">F_Lat</attalias><attrtype Sync="TRUE">Double</attrtype><attwidth Sync="TRUE">8</attwidth><atprecis Sync="TRUE">0</atprecis><attscale Sync="TRUE">0</attscale></attr><attr><attrlabl Sync="TRUE">F_Long</attrlabl><attalias Sync="TRUE">F_Long</attalias><attrtype Sync="TRUE">Double</attrtype><attwidth Sync="TRUE">8</attwidth><atprecis Sync="TRUE">0</atprecis><attscale Sync="TRUE">0</attscale></attr><attr><attrlabl Sync="TRUE">SourceID</attrlabl><attalias Sync="TRUE">SourceID</attalias><attrtype Sync="TRUE">Integer</attrtype><attwidth Sync="TRUE">4</attwidth><atprecis Sync="TRUE">0</atprecis><attscale Sync="TRUE">0</attscale></attr><attr><attrlabl Sync="TRUE">SourceOID</attrlabl><attalias Sync="TRUE">SourceOID</attalias><attrtype Sync="TRUE">Integer</attrtype><attwidth Sync="TRUE">4</attwidth><atprecis Sync="TRUE">0</atprecis><attscale Sync="TRUE">0</attscale></attr><attr><attrlabl Sync="TRUE">PosAlong</attrlabl><attalias Sync="TRUE">PosAlong</attalias><attrtype Sync="TRUE">Double</attrtype><attwidth Sync="TRUE">8</attwidth><atprecis Sync="TRUE">0</atprecis><attscale Sync="TRUE">0</attscale></attr><attr><attrlabl Sync="TRUE">SideOfEdge</attrlabl><attalias Sync="TRUE">SideOfEdge</attalias><attrtype Sync="TRUE">Integer</attrtype><attwidth Sync="TRUE">4</attwidth><atprecis Sync="TRUE">0</atprecis><attscale Sync="TRUE">0</attscale></attr><attr><attrlabl Sync="TRUE">SnapX</attrlabl><attalias Sync="TRUE">SnapX</attalias><attrtype Sync="TRUE">Double</attrtype><attwidth Sync="TRUE">8</attwidth><atprecis Sync="TRUE">0</atprecis><attscale Sync="TRUE">0</attscale></attr><attr><attrlabl Sync="TRUE">SnapY</attrlabl><attalias Sync="TRUE">SnapY</attalias><attrtype Sync="TRUE">Double</attrtype><attwidth Sync="TRUE">8</attwidth><atprecis Sync="TRUE">0</atprecis><attscale Sync="TRUE">0</attscale></attr><attr><attrlabl Sync="TRUE">Distance</attrlabl><attalias Sync="TRUE">Distance</attalias><attrtype Sync="TRUE">Double</attrtype><attwidth Sync="TRUE">8</attwidth><atprecis Sync="TRUE">0</atprecis><attscale Sync="TRUE">0</attscale></attr></detailed></eainfo><mdDateSt Sync="TRUE">20121120</mdDateSt></metadata>
